servergrimoire/__init__.py
servergrimoire/__main__.py
servergrimoire/app.py
servergrimoire/configmanager.py
servergrimoire/dispatcher.py
servergrimoire/operation/dnschecker.py
servergrimoire/operation/dnslookup.py
servergrimoire/operation/pagechecker.py
servergrimoire/operation/sslverify.py
servergrimoire/plugin.py
servergrimoire-1.8.8.dist-info/entry_points.txt
servergrimoire-1.8.8.dist-info/LICENSE
servergrimoire-1.8.8.dist-info/WHEEL
servergrimoire-1.8.8.dist-info/METADATA
servergrimoire-1.8.8.dist-info/RECORD
