Metadata-Version: 2.1
Name: servergrimoire
Version: 1.8.8
Summary: Package for record and store info about servers and their stuffs
Home-page: https://fundor333.com/servergrimoire/
License: MIT
Keywords: devops,ssl,sysadmin
Author: Fundor333
Author-email: fundor333@fundor333.com
Requires-Python: >=3.8,<4.0
Classifier: Development Status :: 4 - Beta
Classifier: Intended Audience :: Developers
Classifier: Intended Audience :: System Administrators
Classifier: License :: OSI Approved :: MIT License
Classifier: Programming Language :: Python :: 3
Classifier: Programming Language :: Python :: 3.10
Classifier: Programming Language :: Python :: 3.8
Classifier: Programming Language :: Python :: 3.9
Classifier: Topic :: System :: Networking :: Monitoring
Requires-Dist: Click (>=7.1.2,<8.0.0)
Requires-Dist: dnspython (>=2.1.0,<3.0.0)
Requires-Dist: pyOpenssl (>=20.0.1,<21.0.0)
Requires-Dist: python-whois (>=0.7.3,<0.8.0)
Requires-Dist: requests (>=2.25.1,<3.0.0)
Requires-Dist: rich (>=9.13.0,<10.0.0)
Project-URL: Repository, https://github.com/fundor333/servergrimoire
